gempa_terkini/__init__.py
Indonesia_earthquake_live_report-0.0.2.dist-info/LICENSE
Indonesia_earthquake_live_report-0.0.2.dist-info/METADATA
Indonesia_earthquake_live_report-0.0.2.dist-info/WHEEL
Indonesia_earthquake_live_report-0.0.2.dist-info/top_level.txt
Indonesia_earthquake_live_report-0.0.2.dist-info/RECORD
