Metadata-Version: 2.1
Name: Indonesia_earthquake_live_report
Version: 0.0.2
Summary: This package will get the latest earthquake report from BMKG
Author-email: Antonius Sawung Wulung <sawungwulung7@gmail.com>
Project-URL: Homepage, https://github.com/TaWulung/indonesia-latest-earthquake-report
Classifier: Programming Language :: Python :: 3
Classifier: License :: OSI Approved :: GNU General Public License v3 (GPLv3)
Classifier: Operating System :: OS Independent
Classifier: Development Status :: 4 - Beta
Requires-Python: >=3.7
License-File: LICENSE
